llmtrack/__init__.py
llmtrack/config.py
llmtrack/hf_model.py
llmtrack/language_model.py
llmtrack/logging_util.py
llmtrack/openai_model.py
llmtrack-1.0.0.dist-info/METADATA
llmtrack-1.0.0.dist-info/WHEEL
llmtrack-1.0.0.dist-info/top_level.txt
llmtrack-1.0.0.dist-info/RECORD
