Metadata-Version: 2.1
Name: llmtrack
Version: 1.0.0
Summary: A concise description of your package.
Home-page: https://github.com/xinzhel/llmtrack
Author: Xinzhe Li
Author-email: xinzheli212@gmail.com
License: MIT
Classifier: Programming Language :: Python :: 3
Classifier: License :: OSI Approved :: MIT License
Classifier: Operating System :: OS Independent
Requires-Python: >=3.6
Requires-Dist: diskcache >=5.6.3
Requires-Dist: openai >=1.23.1
Requires-Dist: numpy >=1.26.4
Requires-Dist: groq >=0.11.0
